raspberry_p0
raspberry_p0/configurations
raspberry_p0/physical
