Metadata-Version: 1.1
Name: PedalPi-Raspberry-P0
Version: 0.2.1
Summary: A simple physical controller for change and view the current pedalboard
Home-page: https://github.com/PedalPi/Raspberry-P0
Author: Paulo Mateus Moura da Silva (SrMouraSilva)
Author-email: mateus.moura@hotmail.com
License: Apache Software License v2
Keywords: pedal-pi mod-host lv2 audio plugins-manager raspberry
Platform: Linux
Classifier: Development Status :: 3 - Alpha
Classifier: Intended Audience :: Developers
Classifier: License :: OSI Approved :: Apache Software License
Classifier: Topic :: Multimedia :: Sound/Audio
Classifier: Programming Language :: Python :: 3.4
Classifier: Programming Language :: Python :: 3.5
Classifier: Programming Language :: Python :: 3.6
